{
   "abstract" : "A libcurl based HTTP backend for ElasticSearch",
   "author" : [
      "Clinton Gormley <drtech@cpan.org>"
   ],
   "dynamic_config" : 0,
   "generated_by" : "Dist::Zilla version 4.300000, CPAN::Meta::Converter version 2.110930",
   "license" : [
      "perl_5"
   ],
   "meta-spec" : {
      "url" : "http://search.cpan.org/perldoc?CPAN::Meta::Spec",
      "version" : "2"
   },
   "name" : "ElasticSearch-Transport-Curl",
   "prereqs" : {
      "build" : {
         "requires" : {
            "Module::Build" : "0.3601"
         }
      },
      "configure" : {
         "requires" : {
            "Module::Build" : "0.38"
         }
      },
      "runtime" : {
         "requires" : {
            "ElasticSearch" : "0.41",
            "ElasticSearch::Transport" : 0,
            "Encode" : 0,
            "WWW::Curl::Easy" : 0,
            "parent" : 0,
            "strict" : 0,
            "warnings" : 0
         }
      },
      "test" : {
         "requires" : {
            "Test::More" : 0
         }
      }
   },
   "release_status" : "stable",
   "resources" : {
      "bugtracker" : {
         "web" : "https://github.com/clintongormley/ElasticSearch-Curl/issues"
      },
      "homepage" : "https://metacpan.org/module/ElasticSearch",
      "repository" : {
         "type" : "git",
         "url" : "git://github.com/clintongormley/ElasticSearch-Curl.git",
         "web" : "https://github.com/clintongormley/ElasticSearch-Curl"
      }
   },
   "version" : "0.02"
}

